{
  "current_date": "2025-08-24",
  "当前日期": "2025-08-24",
  "阶段": "月末",
  "已加班小时数": "66.6",
  "剩余需加班": "3.4",
  "剩余工作日": "5",
  "工作日每日目标(h)": "0.0",
  "周六剩余": "1",
  "周末冲刺(h)": "-",
  "来源": "兜底",
  "AI错误": "401 Client Error: Unauthorized for url: https://api.siliconflow.cn/v1/chat/completions",
  "this_month_holiday": "📅 本月无官方公共假期，继续搬砖！",
  "prev_holiday": "⏳ 上一个假期【端午节】已过去 83 天，怀念ing～",
  "next_holiday": "🚀 下一个假期【国庆节】还有 38 天，倒计时开始！",
  "already_overtime_hours": 66.6,
  "advice": "叮！2025-08-24 打卡，月末模式已就位。\n当前已肝 66.6h / 70h，缺口 3.4h，相当于 2.3 个《甄嬛传》全集😵‍💫。\n工作日方案：每天 18:00 往后加 0.0h，大概 18:00 收工，坚持 5 天就能上岸！\n周六方案：还有 1 个周六，每趟 ≥6h，共可回血 ≥6h。\n月末冲刺！周六狂飙+工作日补刀，胜利在望🚩。\n\n📅 本月无官方公共假期，继续搬砖！\n⏳ 上一个假期【端午节】已过去 83 天，怀念ing～\n🚀 下一个假期【国庆节】还有 38 天，倒计时开始！"
}